hduq/__init__.py
hduq/cgh.py
hduq/cli.py
hduq/spadeutils.py
hduq/assets/__init__.py
hduq/assets/fx2.npy
hduq/controller/__init__.py
hduq/controller/core.py
hduq/controller/api/ALP4.py
hduq/controller/api/__init__.py
hduq/controller/api/dcam.py
hduq/controller/api/dcamapi4.py
hduq/tools/__init__.py
hduq/tools/cache.py
hduq/tools/gifshow.py
hduq/tools/io.py
hduq/tools/parallelize.py
hduq-0.0.8.dist-info/METADATA
hduq-0.0.8.dist-info/WHEEL
hduq-0.0.8.dist-info/top_level.txt
hduq-0.0.8.dist-info/RECORD
