Metadata-Version: 2.4
Name: hduq
Version: 0.0.8
Summary: HDUQ Python utils
Author: Chao-Ning Hu
License: GPLv3
Requires-Python: >=3.9
Requires-Dist: numpy
Requires-Dist: pandas
Requires-Dist: scipy
Requires-Dist: Pillow
Requires-Dist: opencv-python
Requires-Dist: dask
Requires-Dist: psutil
Dynamic: author
Dynamic: license
Dynamic: requires-dist
Dynamic: requires-python
Dynamic: summary
